<newspaperCopy>
  <date>
    <year>1895</year>
    <month>11</month>
    <day>22</day>
  </date>
  <ID>328535</ID>
  <stories>
    <story>
      <number>0</number>
      <text>Das große Eisenbahn-Englück am Pariser des Buches ia usem Trial, Pargelestuichte gleicheich, heiss ie hardt(Pianist). Das Programm ist sehr reichhaltig.</text>
      <exceptionalNormal/>
    </story>
    <story>
      <number>1</number>
      <text>Grundstück-Verkauf. Wie schon kurz gemeldet, sind die in wei zu beiden Seiten der Herwarthstraße, in unmittelbarer Nähe des Kaiser-Wilhelm-Ringes, die drei andern an der am Stadtgarten hrung wiederum übergeben. Der h. Paulinus zählt zu den ältesten Heili gen Köln's. Nach Aegidius von Orval war er ein Schüler des h. Ma ternis und wurde gegen Ende des dritten Jahrhunderts Mapmigt in grustager Bos, Genget dusche Der k. Acbd weiche</text>
      <exceptionalNormal/>
    </story>
    <story>
      <number>2</number>
      <text>e. Sioilatzede Kheskche eshgeuie, Shescheicer she 1e.</text>
      <exceptionalNormal/>
    </story>
    <story>
      <number>3</number>
      <text>Kalk, 21.N0v.95. Unter allgemeiner Betheiligung feierte der hiesige Arbeiter-Verein am gestrigen Tage sein zehntes Stiftungs fest, am Morgen durch ein feierliches Hochamt, welches für die lebenden und verstorbenen Vereinsmitglieder gehalten wurde, am Nachmittag mit Dank-Andacht und am Abend mit einer Festversammlung. Die Feier erhielt ihre besondere Weihe durch die Anwesenheit des Hru. Weihbischofs Dr., Schmitz. Sowohl von der Kanzel als auch in der Abend-Versammlung verbreitete sich der hochwürdigste Herr in einer längern Ansprache über die jetzt so brennend gewordene sociale Frage, insbesondere über den die jetzt so brennend gewordene sociale Früge, insessondete nber Segen der Arbeit, und den hohen Werth und Nutzer, des Vereinslebens #uf christlichen Untergrunde.</text>
      <exceptionalNormal/>
    </story>
  </stories>
</newspaperCopy>
