<newspaperCopy>
  <date>
    <year>1909</year>
    <month>12</month>
    <day>2</day>
  </date>
  <ID>399192</ID>
  <stories>
    <story>
      <number>0</number>
      <text>Windthorstbund. Heute abend findet in der Restauration Wingen eine Versammlung statt, in der über die Gründung eines Windthorstbundes in Lindenthal beschlossen werden soll. Die Versammlung beginnt um 9 Uhr; tüchtige Redner sind gewonnen. Um zahlreichen Besuch wird gebeten.. Wie 2 4 Jugendlicher Straßeräuber! Vorgestern entriß in der Bachemerstraße ein etwa 16jähriger Junge einem etwa achtährigen Mädchen einer Arbeiterfamilie, das für seine Eltern Einkäufe machen sollte, das Portemonnaie mit über 3 M. und entlief damit.</text>
      <exceptionalNormal/>
    </story>
    <story>
      <number>1</number>
      <text>Eine Revision der Maß- und Wägegeräte findet im Laufe der Monate Dezember und Januar bei den Gewerbetreibenden des 24. und 29. Polizeireviers stalt.</text>
      <exceptionalNormal/>
    </story>
    <story>
      <number>2</number>
      <text>Abgewiesen. Geheimer Kommerzienrat Julius Vorster hat 0 Die Böberlegung der Deutzer Brückenrampe ist soweit fertiggestellt, daß heute in der Frühe der Straßenbarn- und Fuhrwerksverkehr über den stromseitigen, den höher gelegenen Teil geleitet werden konnte. Trotz der umsichtigen und energischen Arbeiten lassen sich Verkehrsbehinderungen nicht vermeiden. Die Straßenbahnwagen erleiden aule Verspätungen, und die Fuhrwerke, besonders die unbeladenen, tun gut, die Schiffbarücke zu benutzen, während schwer beladene Fahrzeuge mit Vorspann versehen werden müssen, da die neu angeschüttete Fahrbahn doch hier und da sinken und sich unliebsame Weiterungen ergeben könnten. Nunmehr wird die andere Hälfte höher gelegt.</text>
      <exceptionalNormal/>
    </story>
  </stories>
</newspaperCopy>
